<?xml version="1.0" encoding="utf-8"?>
<!DOCTYPE hibernate-mapping PUBLIC "-//Hibernate/Hibernate Mapping DTD 3.0//EN"
"http://hibernate.sourceforge.net/hibernate-mapping-3.0.dtd">
<!-- 
    Mapping file autogenerated by MyEclipse Persistence Tools
-->
<hibernate-mapping>
    <class name="com.spring05.pojo.Dept" table="DEPT" schema="SCOTT">
        <id name="deptno" type="java.lang.Integer">
            <column name="DEPTNO" precision="2" scale="0" />
            <generator class="assigned" />
        </id>
        <property name="dname" type="java.lang.String">
            <column name="DNAME" length="14" />
        </property>
        <property name="loc" type="java.lang.String">
            <column name="LOC" length="13" />
        </property>
        <set name="emps" lazy="true" inverse="true">
        	<!-- Emp中外键字段 -->
        	<key column="DEPTNO"></key>
        	<!-- 集合类型 -->
        	<one-to-many class="com.spring05.pojo.Emp"/>
        </set>
    </class>
</hibernate-mapping>
